{
    "ce004ae6c8e433d458d3656eec8b3b49": [
        [
            540,
            78,
            0
        ]
    ],
    "ce00c046e81dc4c27b6b4015daa8f7bf": [
        [
            339,
            249,
            0
        ]
    ],
    "ce01f47ffe615db545d38a72e5198f0c": [
        [
            43,
            86,
            0
        ]
    ],
    "ce035479dc76505b4c65b620a9271bbd": [
        [
            388,
            75,
            0
        ]
    ],
    "ce0b59a09c443768313f68c582341ed0": [
        [
            186,
            66,
            0
        ]
    ],
    "ce0b93a30cc26f77f7095293fca49386": [
        [
            211,
            6,
            0
        ]
    ],
    "ce0d2bc1affddf2a5eca0cb0086cbe8d": [
        [
            477,
            83,
            0
        ]
    ],
    "ce0e46c2d5a9112b60df11c33ab662f9": [
        [
            510,
            76,
            0
        ]
    ],
    "ce10b47b13df946a13872a2aee167f6d": [
        [
            230,
            98,
            0
        ]
    ],
    "ce10f6dc5d80f126b17a92253a17f02e": [
        [
            380,
            106,
            0
        ]
    ],
    "ce11bdd5d1c97e96fd4fd234e10eeda7": [
        [
            348,
            237,
            0
        ]
    ],
    "ce167b3f11f3961f99148cc4ad8b50ff": [
        [
            34,
            112,
            0
        ]
    ],
    "ce18f87bd2d6bdb199b636f479ecec3d": [
        [
            372,
            212,
            0
        ]
    ],
    "ce19e7041c67f2f7a97bbdf43043764d": [
        [
            314,
            237,
            0
        ]
    ],
    "ce1ee1688912b6b29c1737f2feb7dd6b": [
        [
            26,
            50,
            0
        ]
    ],
    "ce24792ad6835e2a009883aa805120b7": [
        [
            330,
            79,
            0
        ]
    ],
    "ce254045f46769c39ece8c43b2dc137a": [
        [
            455,
            137,
            0
        ]
    ],
    "ce256d1b29be80774af3081e9970f859": [
        [
            420,
            159,
            0
        ]
    ],
    "ce28fd522973331ee4f2ebca60f61ec4": [
        [
            569,
            73,
            0
        ]
    ],
    "ce2d09b958c9a3d3c11e81d200499003": [
        [
            445,
            152,
            0
        ]
    ],
    "ce2e097c2d9e5239ad921be24673be69": [
        [
            361,
            90,
            0
        ]
    ],
    "ce2e17fda5afca898bc057ef493faba5": [
        [
            213,
            2,
            0
        ]
    ],
    "ce3199d96a5129938df053b0705c493e": [
        [
            256,
            168,
            0
        ]
    ],
    "ce323b685731538fce98d69d927f5c10": [
        [
            359,
            219,
            0
        ]
    ],
    "ce334a308c891894f1ef41650e3fbe81": [
        [
            368,
            114,
            0
        ]
    ],
    "ce3595bfbb04c4a7706681debe77f5aa": [
        [
            504,
            69,
            0
        ]
    ],
    "ce3d5735b672046f7d0547e2ab35c5f8": [
        [
            466,
            115,
            0
        ]
    ],
    "ce46fcfa24c823b944d762189cdcc1ae": [
        [
            213,
            83,
            0
        ]
    ],
    "ce488a0a85ad7c50d7770e144262611b": [
        [
            490,
            137,
            0
        ]
    ],
    "ce49914f985299dd8e63c7162aba6b0c": [
        [
            256,
            167,
            0
        ]
    ],
    "ce49eb44b6e43c0326f7703324212139": [
        [
            478,
            96,
            0
        ]
    ],
    "ce4c60ca7328c16443966d6b8e4f9315": [
        [
            553,
            79,
            0
        ]
    ],
    "ce5057f84a918f2580d41f2692241ca0": [
        [
            512,
            36,
            0
        ]
    ],
    "ce56f86ec29a42108a88a43dff8c63f6": [
        [
            367,
            113,
            0
        ]
    ],
    "ce57b134117355720d3985ce2ccb8898": [
        [
            515,
            169,
            0
        ]
    ],
    "ce5ac1242093b716fb20253be698b0a2": [
        [
            377,
            66,
            0
        ]
    ],
    "ce5b6770792c600ed6a1f266622f39b3": [
        [
            210,
            95,
            0
        ]
    ],
    "ce5c9869bd1fdd33200f9256707fa736": [
        [
            313,
            61,
            0
        ]
    ],
    "ce69f0b136b62c134f19c3a143de9fd0": [
        [
            223,
            80,
            0
        ]
    ],
    "ce6bc7819aedf0ec142244aa2894ec08": [
        [
            368,
            215,
            0
        ]
    ],
    "ce6f01ad7acbd2ec8a3b79320d90d9f4": [
        [
            411,
            175,
            0
        ]
    ],
    "ce7052493baf9ba624ee374158cbad33": [
        [
            207,
            8,
            0
        ]
    ],
    "ce70ed37ceb13fb240e00a08abb7309b": [
        [
            307,
            191,
            0
        ]
    ],
    "ce728d2cfe393d060788b9702d157f69": [
        [
            599,
            70,
            0
        ]
    ],
    "ce76b87731f24b6c8c40eabdc21e18fc": [
        [
            317,
            188,
            0
        ]
    ],
    "ce771d8e37cdda5a54970ff0dadbb0ce": [
        [
            281,
            195,
            0
        ]
    ],
    "ce7fa746154ceec2330d977d88a466b6": [
        [
            383,
            176,
            0
        ]
    ],
    "ce7faf5c2eb96d8d1bb45a9aacf4b466": [
        [
            314,
            203,
            0
        ]
    ],
    "ce88038c5de910293a23047109445b11": [
        [
            217,
            134,
            0
        ]
    ],
    "ce8a9326ae0eced5580756aa50601eb6": [
        [
            42,
            78,
            0
        ]
    ],
    "ce8ae1d11bc459fdfdec9aad4453a769": [
        [
            319,
            196,
            0
        ]
    ],
    "ce8b55520f8cf1fa5517d0b00ac0aea7": [
        [
            110,
            237,
            0
        ]
    ],
    "ce90f7506a95fa5a9d846ef6b7f968d7": [
        [
            232,
            155,
            0
        ]
    ],
    "ce98589c343b4a90f4839218cd2e208c": [
        [
            239,
            177,
            0
        ]
    ],
    "ce9a56144f57831673fcb1500d53286b": [
        [
            353,
            63,
            0
        ]
    ],
    "ce9aeee5ea1a486c0e31e261febf50da": [
        [
            127,
            246,
            0
        ]
    ],
    "ce9c490f62dffc01f559d3cf34bb55cf": [
        [
            312,
            227,
            0
        ]
    ],
    "ce9dee9e310fe02295fda5b0a2ab107e": [
        [
            367,
            42,
            0
        ]
    ],
    "ce9faa8b81c2784d1b0c099e87f5a053": [
        [
            275,
            177,
            0
        ]
    ],
    "cea16391de280fb689ba3ccf5a225f72": [
        [
            484,
            86,
            0
        ]
    ],
    "cea26c73d0de4e1c5a80ffc5806f2a5e": [
        [
            259,
            77,
            0
        ]
    ],
    "cea4cadf74722a04fdb9d1b5afca48ec": [
        [
            246,
            175,
            0
        ]
    ],
    "cea60ce71638e69fd7834a2b60fbcb56": [
        [
            323,
            212,
            0
        ]
    ],
    "cea8af88bbc9c8aac1a60dcbd3da65b1": [
        [
            459,
            37,
            0
        ]
    ],
    "cea8f56fe7ee757dcabccd0ecd63034d": [
        [
            397,
            174,
            0
        ]
    ],
    "cea917cd28997fbdc52508c92edab98e": [
        [
            456,
            145,
            0
        ]
    ],
    "cea9e271adf096df2e41b0b1ad5c4735": [
        [
            138,
            84,
            0
        ]
    ],
    "ceac69ac8fa529ce54d5af8c198fe32d": [
        [
            217,
            109,
            0
        ]
    ],
    "ceacf22531b238a6bf83411e1125c808": [
        [
            197,
            120,
            0
        ]
    ],
    "cead071682e7b52a3ac9d51ef0bd724c": [
        [
            204,
            71,
            0
        ]
    ],
    "ceaf569a5f278b2506c712689c5e8c79": [
        [
            237,
            72,
            0
        ]
    ],
    "ceb55ddc00a4e7feec3607b0f049ff90": [
        [
            56,
            43,
            0
        ]
    ],
    "ceb6322053df7b715c62c179a9649e6b": [
        [
            57,
            75,
            0
        ]
    ],
    "ceb8628730e4ca7afccd554fe71c409e": [
        [
            170,
            75,
            0
        ]
    ],
    "ceb876ddb556481ccd9ab2d85691efda": [
        [
            222,
            160,
            0
        ]
    ],
    "cec1f1e24c4c4190802fa673e5f18031": [
        [
            271,
            76,
            0
        ]
    ],
    "cec43e04bf74ca0c613437cb1810006f": [
        [
            39,
            46,
            0
        ]
    ],
    "cec50c53e80b0992383ae79e1fe034b0": [
        [
            356,
            126,
            0
        ]
    ],
    "cec6a4e1a7179c76ed20dc9a9cc8310a": [
        [
            504,
            180,
            0
        ]
    ],
    "cec7f6f3e053f0015c06749b0dbc48a8": [
        [
            340,
            79,
            0
        ]
    ],
    "ceca31114fca15e54ce648e24029965a": [
        [
            15,
            41,
            0
        ]
    ],
    "cecbcecc3a5750cab14d59cc376772d6": [
        [
            97,
            209,
            0
        ]
    ],
    "cecce7fa277848b101fd7b0e330666c4": [
        [
            500,
            54,
            0
        ]
    ],
    "ced0d0285acf81212638ab76ddf17968": [
        [
            185,
            111,
            0
        ]
    ],
    "ced0ffaad621f8b5729eac26f003156b": [
        [
            220,
            103,
            0
        ]
    ],
    "ced5374322ca0273bd9aff490c736fd5": [
        [
            346,
            228,
            0
        ]
    ],
    "ced61c3d980417bd604e928ae6b8fc4d": [
        [
            237,
            71,
            0
        ]
    ],
    "ced620cfea91ea03e1e9b7a48d6ddcc7": [
        [
            356,
            227,
            0
        ]
    ],
    "ced6bd160db5e3332db22f7f68c368d4": [
        [
            272,
            165,
            0
        ]
    ],
    "ced70475790e936045120832a262756c": [
        [
            495,
            62,
            0
        ]
    ],
    "ced82f1a07c368e2790fc098f3f603ba": [
        [
            365,
            200,
            0
        ]
    ],
    "cedb94afe3a2ef1ce35c28e0fd257256": [
        [
            507,
            46,
            0
        ]
    ],
    "cedcbf5bf7243254498c6ea8279befa4": [
        [
            428,
            64,
            0
        ]
    ],
    "cedcc277389267582854fcfc4af7a642": [
        [
            156,
            62,
            0
        ]
    ],
    "cee3a975f5a09dc68770733257aad2b4": [
        [
            475,
            67,
            0
        ]
    ],
    "cee40a5030a717c7408cc18144d93cc3": [
        [
            137,
            89,
            0
        ]
    ],
    "cee8a08765d616167657f55beeb635e8": [
        [
            519,
            147,
            0
        ]
    ],
    "ceea522ecaa4d7f52c383fb34d016e90": [
        [
            460,
            47,
            0
        ]
    ],
    "cef3d8b40a00a94f6df1d296bab740e2": [
        [
            388,
            176,
            0
        ]
    ]
}
